src/__init__.py
src/jflMLPack.py
jflmlpack-0.0.1.dist-info/METADATA
jflmlpack-0.0.1.dist-info/WHEEL
jflmlpack-0.0.1.dist-info/licenses/LICENSE
jflmlpack-0.0.1.dist-info/RECORD
